bp_runner/__init__.py
bp_runner/main.py
bp_runner/bin/bp-runner-time
bp_runner-0.1.2.dist-info/licenses/LICENSE
bp_runner-0.1.2.dist-info/METADATA
bp_runner-0.1.2.dist-info/WHEEL
bp_runner-0.1.2.dist-info/entry_points.txt
bp_runner-0.1.2.dist-info/top_level.txt
bp_runner-0.1.2.dist-info/RECORD
