Metadata-Version: 2.4
Name: bp-runner
Version: 0.1.2
Summary: task Runner
Author-email: birds <cg626@163.com>
Classifier: Programming Language :: Python :: 3
Classifier: Operating System :: OS Independent
Requires-Python: >=3.12
License-File: LICENSE
Requires-Dist: bp-config>=0.1.2
Requires-Dist: PyYAML>=6.0
Requires-Dist: toml>=0.10.2
Dynamic: license-file
